.hgignore
.hgtags
AUTHORS
LICENSE
setup.py
django_oauth.egg-info/PKG-INFO
django_oauth.egg-info/SOURCES.txt
django_oauth.egg-info/dependency_links.txt
django_oauth.egg-info/not-zip-safe
django_oauth.egg-info/top_level.txt
examples/__init__.py
examples/provider/__init__.py
examples/provider/manage.py
examples/provider/settings.py
examples/provider/urls.py
oauth/__init__.py
oauth/oauth.py
oauth_provider/__init__.py
oauth_provider/admin.py
oauth_provider/consts.py
oauth_provider/decorators.py
oauth_provider/managers.py
oauth_provider/models.py
oauth_provider/stores.py
oauth_provider/tests.py
oauth_provider/urls.py
oauth_provider/utils.py
oauth_provider/views.py
