Metadata-Version: 1.0
Name: django-oauth
Version: 1.0
Summary: Support of OAuth in Django.
Home-page: http://code.welldev.org/django-oauth/
Author: David Larlet
Author-email: david@larlet.fr
License: UNKNOWN
Platform: UNKNOWN
Classifier: Development Status :: 5 - Production/Stable
Classifier: Environment :: Web Environment
Classifier: Intended Audience :: Developers
Classifier: License :: OSI Approved :: BSD License
Classifier: Operating System :: OS Independent
Classifier: Programming Language :: Python
Classifier: Framework :: Django
